segno_ui/__init__.py
segno_ui/segno_ui.py
segno_ui-1.0.5.data/scripts/segno_ui.py
segno_ui-1.0.5.dist-info/LICENSE
segno_ui-1.0.5.dist-info/METADATA
segno_ui-1.0.5.dist-info/WHEEL
segno_ui-1.0.5.dist-info/top_level.txt
segno_ui-1.0.5.dist-info/RECORD
