Metadata-Version: 2.1
Name: segno_ui
Version: 1.0.5
Summary: Monitor udev events like usb devices being connected, and execute actions upon evnet
Home-page: https://github.com/netinvent/segno_ui
Author: NetInvent - Orsiris de Jong
Author-email: contact@netinvent.fr
License: BSD
Keywords: segnp,qrcode,gui,event,connect,plugged
Classifier: Development Status :: 5 - Production/Stable
Classifier: Intended Audience :: End Users/Desktop
Classifier: Topic :: Multimedia :: Graphics
Classifier: Topic :: Printing
Classifier: Topic :: Software Development :: Libraries :: Python Modules
Classifier: Topic :: Utilities
Classifier: Programming Language :: Python
Classifier: Programming Language :: Python :: 3
Classifier: Programming Language :: Python :: Implementation :: CPython
Classifier: Programming Language :: Python :: Implementation :: PyPy
Classifier: Operating System :: OS Independent
Classifier: License :: OSI Approved :: BSD License
Requires-Python: >=3.6
License-File: LICENSE
Requires-Dist: segno
Requires-Dist: FreeSimpleGUI
